inmanta_plugins/vyos/__init__.py
inmanta_plugins/vyos/setup.cfg
inmanta_plugins/vyos/model/_init.cf
inmanta_plugins/vyos/model/firewall.cf
inmanta_plugins/vyos/model/openstackext.cf
inmanta_plugins/vyos/model/routemap.cf
inmanta_plugins/vyos/model/vpn.cf
inmanta_plugins/vyos/templates/bridge.j2
inmanta_plugins/vyos/templates/dhcp.j2
inmanta_plugins/vyos/templates/espgroup.j2
inmanta_plugins/vyos/templates/firewall_address_group.j2
inmanta_plugins/vyos/templates/firewall_network_group.j2
inmanta_plugins/vyos/templates/firewall_port_group.j2
inmanta_plugins/vyos/templates/firewall_ruleset.j2
inmanta_plugins/vyos/templates/hostname.j2
inmanta_plugins/vyos/templates/ikegroup.j2
inmanta_plugins/vyos/templates/interface.j2
inmanta_plugins/vyos/templates/ipsecoptions.j2
inmanta_plugins/vyos/templates/lointerface.j2
inmanta_plugins/vyos/templates/masq.j2
inmanta_plugins/vyos/templates/ospf.j2
inmanta_plugins/vyos/templates/policy_route_rule.j2
inmanta_plugins/vyos/templates/routemap.j2
inmanta_plugins/vyos/templates/rsakey.j2
inmanta_plugins/vyos/templates/shaper.j2
inmanta_plugins/vyos/templates/site2site.j2
inmanta_plugins/vyos/templates/tunnel.j2
inmanta_plugins/vyos/templates/vif.j2
inmanta_module_vyos-3.0.12.dist-info/LICENSE
inmanta_module_vyos-3.0.12.dist-info/METADATA
inmanta_module_vyos-3.0.12.dist-info/WHEEL
inmanta_module_vyos-3.0.12.dist-info/top_level.txt
inmanta_module_vyos-3.0.12.dist-info/RECORD
